pageo/__init__.py
pageo/errors.py
pageo/base_page/__init__.py
pageo/base_page/base_page.py
pageo/base_page/meta_base_page.py
pageo/locators/__init__.py
pageo/locators/abstract_locator.py
pageo/locators/class_name_locator.py
pageo/locators/css_locator.py
pageo/locators/id_locator.py
pageo/locators/link_text_locator.py
pageo/locators/name_locator.py
pageo/locators/partial_link_text_locator.py
pageo/locators/tag_name_locator.py
pageo/locators/xpath_locator.py
pageo/utils/__init__.py
pageo/utils/map_dict.py
pageo/utils/protocol_setter.py
tests/integrations/__init__.py
tests/integrations/test_package.py
tests/integrations/test_page/__init__.py
tests/integrations/test_page/test_page.py
tests/units/__init__.py
tests/units/base_page/__init__.py
tests/units/base_page/test_base_page.py
pageo-0.3.1.dist-info/LICENSE
pageo-0.3.1.dist-info/METADATA
pageo-0.3.1.dist-info/WHEEL
pageo-0.3.1.dist-info/top_level.txt
pageo-0.3.1.dist-info/RECORD
