Metadata-Version: 2.1
Name: pageo
Version: 0.3.1
Summary: Библиотека на базе Selenium с расширенным функционалом. Предназначена для работы с любым веб-сайтом и его страницами
Author: dmitry
Author-email: dmitryvshivtsev@gmail.com
Classifier: License :: OSI Approved :: MIT License
Classifier: Programming Language :: Python :: 3.10
Classifier: Programming Language :: Python :: 3.11
Classifier: Operating System :: MacOS :: MacOS X
Classifier: Operating System :: Microsoft :: Windows
Classifier: Operating System :: POSIX
License-File: LICENSE
Requires-Dist: pytest >=7.4.0
Requires-Dist: selenium >=4.10.0
